composennent/__init__.py
composennent/models/__init__.py
composennent/models/base.py
composennent/models/bert.py
composennent/models/gpt.py
composennent/models/nlp_base.py
composennent/models/transformer.py
composennent/models/methods/__init__.py
composennent/modules/__init__.py
composennent/modules/block.py
composennent/modules/memory.py
composennent/modules/sequential.py
composennent/modules/attention/__init__.py
composennent/modules/attention/masks.py
composennent/modules/attention/multi_head.py
composennent/modules/decoders/__init__.py
composennent/modules/decoders/causal.py
composennent/modules/decoders/cross_attention.py
composennent/modules/embeddings/__init__.py
composennent/modules/embeddings/feature.py
composennent/modules/embeddings/patch.py
composennent/modules/embeddings/token.py
composennent/modules/encoders/__init__.py
composennent/modules/encoders/bidirectional.py
composennent/modules/experts/__init__.py
composennent/modules/experts/expert_layer.py
composennent/modules/experts/router.py
composennent/modules/feedforward/__init__.py
composennent/modules/feedforward/geglu.py
composennent/modules/feedforward/glu.py
composennent/modules/feedforward/mlp.py
composennent/modules/feedforward/reglu.py
composennent/modules/feedforward/swiglu.py
composennent/modules/positional/__init__.py
composennent/modules/positional/absolute.py
composennent/modules/positional/relative.py
composennent/modules/positional/rotary.py
composennent/nlp/__init__.py
composennent/nlp/tokenizers/__init__.py
composennent/nlp/tokenizers/base.py
composennent/nlp/tokenizers/huggingface.py
composennent/nlp/tokenizers/sentencepiece.py
composennent/nlp/tokenizers/wordpiece.py
composennent/nlp/transformers/__init__.py
composennent/ocr/__init__.py
composennent/trainer/__init__.py
composennent/trainer/engine.py
composennent/trainer/eval.py
composennent/trainer/instruct_engine.py
composennent/trainer/rlhf.py
composennent/trainer/trainers.py
composennent/trainer/data/collate.py
composennent-0.4.5.dist-info/licenses/LICENSE
composennent-0.4.5.dist-info/METADATA
composennent-0.4.5.dist-info/WHEEL
composennent-0.4.5.dist-info/top_level.txt
composennent-0.4.5.dist-info/RECORD
