Metadata-Version: 2.4
Name: composennent
Version: 0.4.5
Summary: Composable neural network components for building models in PyTorch.
Author-email: Dave <tad9277@gmail.com>
License: MIT
Project-URL: Repository, https://github.com/DataOpsFusion/composennent
Keywords: deep-learning,transformers,pytorch,nlp,vision,machine-learning
Classifier: Development Status :: 3 - Alpha
Classifier: Intended Audience :: Developers
Classifier: Intended Audience :: Science/Research
Classifier: Programming Language :: Python :: 3
Classifier: Programming Language :: Python :: 3.8
Classifier: Programming Language :: Python :: 3.9
Classifier: Programming Language :: Python :: 3.10
Classifier: Programming Language :: Python :: 3.11
Classifier: Programming Language :: Python :: 3.12
Classifier: Topic :: Scientific/Engineering :: Artificial Intelligence
Requires-Python: >=3.8
License-File: LICENSE
Requires-Dist: torch>=2.0.0
Requires-Dist: tqdm>=4.65.0
Provides-Extra: nlp
Requires-Dist: sentencepiece>=0.1.99; extra == "nlp"
Provides-Extra: vision
Requires-Dist: torchvision>=0.15.0; extra == "vision"
Requires-Dist: pillow>=9.0.0; extra == "vision"
Provides-Extra: ocr
Requires-Dist: pytesseract>=0.3.10; extra == "ocr"
Provides-Extra: dev
Requires-Dist: pytest>=7.0.0; extra == "dev"
Requires-Dist: pytest-cov>=4.0.0; extra == "dev"
Requires-Dist: black>=23.0.0; extra == "dev"
Requires-Dist: ruff>=0.1.0; extra == "dev"
Requires-Dist: mypy>=1.0.0; extra == "dev"
Provides-Extra: all
Requires-Dist: composennent[dev,nlp,ocr,vision]; extra == "all"
Dynamic: license-file
